{
  "dataset": "swv08",
  "category": "ABZSWVYN",
  "timestamp": "2025-09-24T15:05:27.538302",
  "workflow_results": {
    "full": {
      "config_name": "full",
      "config": {
        "name": "Full Workflow",
        "description": "Complete workflow with all tools",
        "use_validation": true,
        "use_repair": true,
        "use_optimization": true,
        "max_attempts": 3
      },
      "success": false,
      "makespan": null,
      "schedule": [],
      "repair_iterations": [
        {
          "iteration": 1,
          "makespan": 0,
          "schedule": [],
          "schedule_entries_count": 0,
          "timestamp": "2025-09-24T15:05:27.535831"
        },
        {
          "iteration": 2,
          "makespan": 0,
          "schedule": [],
          "schedule_entries_count": 0,
          "timestamp": "2025-09-24T15:05:27.536084"
        },
        {
          "iteration": 3,
          "makespan": 0,
          "schedule": [],
          "schedule_entries_count": 0,
          "timestamp": "2025-09-24T15:05:27.536272"
        },
        {
          "iteration": 4,
          "makespan": 0,
          "schedule": [],
          "schedule_entries_count": 0,
          "timestamp": "2025-09-24T15:05:27.536422"
        },
        {
          "iteration": 5,
          "makespan": 0,
          "schedule": [],
          "schedule_entries_count": 0,
          "timestamp": "2025-09-24T15:05:27.536553"
        }
      ],
      "execution_time": 0.0022420883178710938,
      "timestamp": "2025-09-24T15:05:27.536698"
    },
    "no_repair": {
      "config_name": "no_repair",
      "config": {
        "name": "No Repair Tools",
        "description": "Full workflow without repair tools",
        "use_validation": true,
        "use_repair": false,
        "use_optimization": true,
        "max_attempts": 3
      },
      "success": false,
      "makespan": null,
      "schedule": [],
      "repair_iterations": [],
      "execution_time": 0.00011515617370605469,
      "timestamp": "2025-09-24T15:05:27.537030"
    },
    "no_validation": {
      "config_name": "no_validation",
      "config": {
        "name": "No Validation Tools",
        "description": "Full workflow without validation tools",
        "use_validation": false,
        "use_repair": true,
        "use_optimization": true,
        "max_attempts": 3
      },
      "success": false,
      "makespan": null,
      "schedule": [],
      "repair_iterations": [],
      "execution_time": 9.393692016601562e-05,
      "timestamp": "2025-09-24T15:05:27.537256"
    },
    "no_optimization": {
      "config_name": "no_optimization",
      "config": {
        "name": "No Optimization Tools",
        "description": "Full workflow without optimization tools",
        "use_validation": true,
        "use_repair": true,
        "use_optimization": false,
        "max_attempts": 3
      },
      "success": false,
      "makespan": null,
      "schedule": [],
      "repair_iterations": [
        {
          "iteration": 1,
          "makespan": 0,
          "schedule": [],
          "schedule_entries_count": 0,
          "timestamp": "2025-09-24T15:05:27.537472"
        },
        {
          "iteration": 2,
          "makespan": 0,
          "schedule": [],
          "schedule_entries_count": 0,
          "timestamp": "2025-09-24T15:05:27.537597"
        },
        {
          "iteration": 3,
          "makespan": 0,
          "schedule": [],
          "schedule_entries_count": 0,
          "timestamp": "2025-09-24T15:05:27.537691"
        },
        {
          "iteration": 4,
          "makespan": 0,
          "schedule": [],
          "schedule_entries_count": 0,
          "timestamp": "2025-09-24T15:05:27.537782"
        },
        {
          "iteration": 5,
          "makespan": 0,
          "schedule": [],
          "schedule_entries_count": 0,
          "timestamp": "2025-09-24T15:05:27.537877"
        }
      ],
      "execution_time": 0.0006349086761474609,
      "timestamp": "2025-09-24T15:05:27.538016"
    }
  }
}