{
  "iteration": 3,
  "makespan": 74,
  "schedule": [
    {
      "job": "Job13",
      "step": 1,
      "machine": "Machine2",
      "start": 0,
      "end": 3,
      "duration": 3
    },
    {
      "job": "Job2",
      "step": 1,
      "machine": "Machine3",
      "start": 0,
      "end": 6,
      "duration": 6
    },
    {
      "job": "Job20",
      "step": 1,
      "machine": "Machine3",
      "start": 6,
      "end": 15,
      "duration": 9
    },
    {
      "job": "Job8",
      "step": 1,
      "machine": "Machine3",
      "start": 15,
      "end": 74,
      "duration": 59
    }
  ],
  "schedule_entries_count": 4,
  "timestamp": "2025-09-24T15:05:14.223584"
}